AUTHORS
ChangeLog
LICENSE
MANIFEST.in
README.rst
requirements.txt
setup.cfg
setup.py
leonardo_ckeditor/__init__.py
leonardo_ckeditor/config.py
leonardo_ckeditor.egg-info/PKG-INFO
leonardo_ckeditor.egg-info/SOURCES.txt
leonardo_ckeditor.egg-info/dependency_links.txt
leonardo_ckeditor.egg-info/not-zip-safe
leonardo_ckeditor.egg-info/pbr.json
leonardo_ckeditor.egg-info/requires.txt
leonardo_ckeditor.egg-info/top_level.txt
leonardo_ckeditor/static/leonardo_ckeditor/js/ckeditor-modal-init.js
requirements/default.txt