Metadata-Version: 1.1
Name: leonardo-ckeditor
Version: 1.0.0a6
Summary: CKEditor for Leonardo CMS
Home-page: https://github.com/leonardo-modules/leonardo-ckeditor
Author: Michael Kuty
Author-email: UNKNOWN
License: UNKNOWN
Platform: UNKNOWN
Classifier: Development Status :: 5 - Production/Stable
Classifier: Framework :: Django
Classifier: Intended Audience :: Developers
Classifier: License :: OSI Approved :: BSD License
Classifier: Operating System :: OS Independent
Classifier: Programming Language :: Python
Classifier: Programming Language :: Python :: 2.6
Classifier: Programming Language :: Python :: 2.7
Classifier: Programming Language :: Python :: 3
Classifier: Programming Language :: Python :: 3.3
Classifier: Programming Language :: Python :: 3.4
Classifier: Topic :: Software Development
Classifier: Topic :: Software Development :: Libraries :: Application Frameworks
